{
    "lists": [
        {
            "id": "1",
            "name": "My Day",
            "icon": "cloud-sun",
            "color": "normal"
        },
        {
            "id": "2",
            "name": "Important",
            "icon": "star",
            "color": "normal"
        },
        {
            "id": "3",
            "name": "Planned",
            "icon": "calendar-alt",
            "color": "normal"
        },
        {
            "id": "4",
            "name": "Flagged Email",
            "icon": "flag",
            "color": "red-text"
        },
        {
            "id": "5",
            "name": "Tasks",
            "icon": "home",
            "color": "blue-text"
        },
        {
            "id": "6",
            "name": "Daily Routine",
            "icon": "list",
            "color": "blue-text"
        },
        {
            "id": "7",
            "name": "Family",
            "icon": "users",
            "color": "normal"
        },
        {
            "id": "8",
            "name": "Learn",
            "icon": "list",
            "color": "green-text"
        },
        {
            "id": "9",
            "name": "Chores",
            "icon": "list",
            "color": "red-text"
        },
        {
            "id": "10",
            "name": "Wealth",
            "icon": "money-bill-alt",
            "color": "normal"
        },
        {
            "id": "11",
            "name": "Spirit",
            "icon": "fire-alt",
            "color": "red-text"
        },
        {
            "id": "12",
            "name": "Health",
            "icon": "hospital",
            "color": "normal"
        }
    ],
    "tasks": [
        {
            "id": "1",
            "listId": "3",
            "title": "Integrate Redux with assessment project",
            "completed": true
        },
        {
            "id": "2",
            "listId": "1",
            "title": "Go to Software Design Meetup",
            "completed": true
        },
        {
            "id": "3",
            "listId": "8",
            "title": "Read or watch some tutorials on Redux",
            "completed": true
        },
        {
            "id": "4",
            "listId": "8",
            "title": "Learn React Hooks & Context",
            "completed": false
        },
        {
            "id": "5",
            "listId": "3",
            "title": "Add form fields for adding and updating tasks and lists",
            "completed": false
        },
        {
            "id": "6",
            "listId": "3",
            "title": "Use a package to generate random IDs for lists and tasks",
            "completed": false
        },
        {
            "id": "7",
            "listId": "3",
            "title": "Autosuggest list names from Lists when creating Tasks",
            "completed": false
        }
    ],
    "activeList": "1"
}